ypywidgets/__init__.py
ypywidgets/comm.py
ypywidgets/py.typed
ypywidgets/reactive.py
ypywidgets/widget.py
ypywidgets-0.9.7.dist-info/METADATA
ypywidgets-0.9.7.dist-info/WHEEL
ypywidgets-0.9.7.dist-info/licenses/LICENSE
ypywidgets-0.9.7.dist-info/RECORD
