Metadata-Version: 2.4
Name: ypywidgets
Version: 0.9.7
Summary: Y-based Jupyter widgets for Python
Project-URL: Homepage, https://github.com/davidbrochart/ypywidgets
Author-email: David Brochart <david.brochart@gmail.com>
License-Expression: MIT
License-File: LICENSE
Keywords: jupyter,widgets,yjs
Requires-Python: >=3.8
Requires-Dist: comm<1,>=0.1.4
Requires-Dist: pycrdt<0.13.0,>=0.9.0
Requires-Dist: reacttrs<0.3.0,>=0.2.1
Provides-Extra: dev
Requires-Dist: coverage<8.0.0,>=7.0.0; extra == 'dev'
Requires-Dist: mypy; extra == 'dev'
Requires-Dist: pytest; extra == 'dev'
Requires-Dist: pytest-asyncio; extra == 'dev'
